KTimer/__init__.py
KTimer-1.0.2.dist-info/LICENSE
KTimer-1.0.2.dist-info/METADATA
KTimer-1.0.2.dist-info/WHEEL
KTimer-1.0.2.dist-info/top_level.txt
KTimer-1.0.2.dist-info/RECORD
